sib/__init__.py
sib/cli.py
sib/client.py
sib/package.py
sib/project.py
sib/templates/development/manage.py-tpl
sib/templates/development/packages.yml
sib/templates/development/project_name/__init__.py-tpl
sib/templates/development/project_name/settings.py-tpl
sib/templates/development/project_name/urls.py-tpl
sib/templates/development/project_name/wsgi.py-tpl
sib/templates/package/README.md
sib/templates/package/setup.cfg
sib/templates/package/setup.py-tpl
sib/templates/package/app_name/__init__.py-tpl
sib/templates/package/app_name/admin.py-tpl
sib/templates/package/app_name/apps.py-tpl
sib/templates/package/app_name/models.py-tpl
sib/templates/package/app_name/tests.py-tpl
sib/templates/production/manage.py-tpl
sib/templates/production/packages.yml
sib/templates/production/project_name/__init__.py-tpl
sib/templates/production/project_name/settings.py-tpl
sib/templates/production/project_name/urls.py-tpl
sib/templates/production/project_name/wsgi.py-tpl
sib_manager-0.5.3.dist-info/METADATA
sib_manager-0.5.3.dist-info/WHEEL
sib_manager-0.5.3.dist-info/entry_points.txt
sib_manager-0.5.3.dist-info/top_level.txt
sib_manager-0.5.3.dist-info/RECORD
