Metadata-Version: 2.1
Name: sib-manager
Version: 0.5.3
Summary: StartinBlox Manager
Home-page: https://git.happy-dev.fr/startinblox/sib-installer
Author: Plup
Author-email: plup@plup.io
License: MIT
Platform: UNKNOWN
Classifier: Programming Language :: Python :: 3
Classifier: Operating System :: OS Independent
Requires-Python: >=3.6
Requires-Dist: click
Requires-Dist: pyyaml
Provides-Extra: dev
Requires-Dist: pytest ; extra == 'dev'
Requires-Dist: pytest-cov ; extra == 'dev'
Requires-Dist: pytest-mock ; extra == 'dev'
